LICENSE
MANIFEST.in
README.rst
setup.cfg
setup.py
kiel/__init__.py
kiel/cluster.py
kiel/connection.py
kiel/constants.py
kiel/events.py
kiel/exc.py
kiel/iterables.py
kiel.egg-info/PKG-INFO
kiel.egg-info/SOURCES.txt
kiel.egg-info/dependency_links.txt
kiel.egg-info/requires.txt
kiel.egg-info/top_level.txt
kiel/clients/__init__.py
kiel/clients/client.py
kiel/clients/consumer.py
kiel/clients/grouped.py
kiel/clients/producer.py
kiel/clients/single.py
kiel/compression/__init__.py
kiel/compression/gzip.py
kiel/compression/snappy.py
kiel/protocol/__init__.py
kiel/protocol/coordinator.py
kiel/protocol/describe_groups.py
kiel/protocol/errors.py
kiel/protocol/fetch.py
kiel/protocol/heartbeat.py
kiel/protocol/join_group.py
kiel/protocol/leave_group.py
kiel/protocol/list_groups.py
kiel/protocol/messages.py
kiel/protocol/metadata.py
kiel/protocol/offset.py
kiel/protocol/offset_commit.py
kiel/protocol/offset_fetch.py
kiel/protocol/part.py
kiel/protocol/primitives.py
kiel/protocol/produce.py
kiel/protocol/request.py
kiel/protocol/response.py
kiel/protocol/sync_group.py
kiel/zookeeper/__init__.py
kiel/zookeeper/allocator.py
kiel/zookeeper/party.py
kiel/zookeeper/shared_set.py